AUTHORS.rst
CHANGELOG.rst
LICENSE
MANIFEST.in
README.rst
demo.sh
setup-development.sh
setup.py
test_settings.py
jmbo_skeleton.egg-info/PKG-INFO
jmbo_skeleton.egg-info/SOURCES.txt
jmbo_skeleton.egg-info/dependency_links.txt
jmbo_skeleton.egg-info/not-zip-safe
jmbo_skeleton.egg-info/requires.txt
jmbo_skeleton.egg-info/top_level.txt
project/__init__.py
project/local_settings.py
project/settings.py
project/settings_dev_basic_site.py
project/settings_dev_smart_site.py
project/settings_dev_web_site.py
project/settings_live_admin_site.py
project/settings_live_base.py
project/settings_live_basic_site.py
project/settings_live_smart_site.py
project/settings_live_web_site.py
project/settings_qa_admin_site.py
project/settings_qa_base.py
project/settings_qa_basic_site.py
project/settings_qa_smart_site.py
project/settings_qa_web_site.py
project/urls.py
scripts/create-jmbo-project.sh
scripts/deploy-project.sh
scripts/generate-configs.py
scripts/setup-server.sh
scripts/resources/50x.html
scripts/resources/50x.png
scripts/resources/apache2-webdav.conf
scripts/resources/sentry.conf.py
scripts/resources/supervisor.sentry.conf
scripts/resources/wurfl-2.1.zip
skeleton/__init__.py
skeleton/admin.py
skeleton/models.py
skeleton/urls.py
skeleton/fixtures/README.txt
skeleton/fixtures/sites.json
skeleton/management/__init__.py
skeleton/management/__init__.pyc
skeleton/management/commands/__init__.py
skeleton/management/commands/get_last_foundry_migration.py
skeleton/migrations/0001_initial.py
skeleton/migrations/0001_initial.pyc
skeleton/migrations/__init__.py
skeleton/migrations/__init__.pyc
skeleton/static/basic/css/custom.css
skeleton/static/web/css/custom.css
skeleton/tests/__init__.py