Metadata-Version: 1.1
Name: jmbo-skeleton
Version: 2.0.0
Summary: Create a Jmbo project environment quickly. Includes a Jmbo demo application.
Home-page: UNKNOWN
Author: Praekelt Consulting
Author-email: dev@praekelt.com
License: BSD
Platform: UNKNOWN
Classifier: Programming Language :: Python
Classifier: License :: OSI Approved :: BSD License
Classifier: Development Status :: 4 - Beta
Classifier: Operating System :: OS Independent
Classifier: Framework :: Django
Classifier: Intended Audience :: Developers
Classifier: Topic :: Internet :: WWW/HTTP :: Dynamic Content
